<annotation>
	<folder></folder>
	<filename>000063_jpg.rf.36cd08bfcd8c651984e3a6c420516f33.jpg</filename>
	<path>000063_jpg.rf.36cd08bfcd8c651984e3a6c420516f33.jpg</path>
	<source>
		<database>roboflow.ai</database>
	</source>
	<size>
		<width>500</width>
		<height>340</height>
		<depth>3</depth>
	</size>
	<segmented>0</segmented>
	<object>
		<name>helmet</name>
		<pose>Unspecified</pose>
		<truncated>0</truncated>
		<difficult>0</difficult>
		<occluded>0</occluded>
		<bndbox>
			<xmin>177</xmin>
			<xmax>208</xmax>
			<ymin>45</ymin>
			<ymax>80</ymax>
		</bndbox>
	</object>
	<object>
		<name>helmet</name>
		<pose>Unspecified</pose>
		<truncated>0</truncated>
		<difficult>0</difficult>
		<occluded>0</occluded>
		<bndbox>
			<xmin>73</xmin>
			<xmax>99</xmax>
			<ymin>42</ymin>
			<ymax>73</ymax>
		</bndbox>
	</object>
</annotation>
