<annotation>
	<folder></folder>
	<filename>000205_jpg.rf.502e71ef61c0bfef87b80e4696cbcf24.jpg</filename>
	<path>000205_jpg.rf.502e71ef61c0bfef87b80e4696cbcf24.jpg</path>
	<source>
		<database>roboflow.ai</database>
	</source>
	<size>
		<width>450</width>
		<height>300</height>
		<depth>3</depth>
	</size>
	<segmented>0</segmented>
	<object>
		<name>helmet</name>
		<pose>Unspecified</pose>
		<truncated>0</truncated>
		<difficult>0</difficult>
		<occluded>0</occluded>
		<bndbox>
			<xmin>163</xmin>
			<xmax>213</xmax>
			<ymin>62</ymin>
			<ymax>112</ymax>
		</bndbox>
	</object>
</annotation>
