<annotation>
	<folder></folder>
	<filename>000776_jpg.rf.57972da42a13a5dc6233670fb0fd2efa.jpg</filename>
	<path>000776_jpg.rf.57972da42a13a5dc6233670fb0fd2efa.jpg</path>
	<source>
		<database>roboflow.ai</database>
	</source>
	<size>
		<width>500</width>
		<height>334</height>
		<depth>3</depth>
	</size>
	<segmented>0</segmented>
	<object>
		<name>helmet</name>
		<pose>Unspecified</pose>
		<truncated>0</truncated>
		<difficult>0</difficult>
		<occluded>0</occluded>
		<bndbox>
			<xmin>226</xmin>
			<xmax>246</xmax>
			<ymin>183</ymin>
			<ymax>208</ymax>
		</bndbox>
	</object>
	<object>
		<name>helmet</name>
		<pose>Unspecified</pose>
		<truncated>0</truncated>
		<difficult>0</difficult>
		<occluded>0</occluded>
		<bndbox>
			<xmin>268</xmin>
			<xmax>288</xmax>
			<ymin>178</ymin>
			<ymax>205</ymax>
		</bndbox>
	</object>
</annotation>
