<annotation>
	<folder></folder>
	<filename>001889_jpg.rf.24687bf68cf1e6a309971bea80d8b48a.jpg</filename>
	<path>001889_jpg.rf.24687bf68cf1e6a309971bea80d8b48a.jpg</path>
	<source>
		<database>roboflow.ai</database>
	</source>
	<size>
		<width>400</width>
		<height>266</height>
		<depth>3</depth>
	</size>
	<segmented>0</segmented>
	<object>
		<name>helmet</name>
		<pose>Unspecified</pose>
		<truncated>0</truncated>
		<difficult>0</difficult>
		<occluded>0</occluded>
		<bndbox>
			<xmin>43</xmin>
			<xmax>146</xmax>
			<ymin>102</ymin>
			<ymax>179</ymax>
		</bndbox>
	</object>
</annotation>
