<annotation>
	<folder></folder>
	<filename>001871_jpg.rf.f2314ce4c4098a630e585b233f3cce8e.jpg</filename>
	<path>001871_jpg.rf.f2314ce4c4098a630e585b233f3cce8e.jpg</path>
	<source>
		<database>roboflow.ai</database>
	</source>
	<size>
		<width>500</width>
		<height>325</height>
		<depth>3</depth>
	</size>
	<segmented>0</segmented>
	<object>
		<name>helmet</name>
		<pose>Unspecified</pose>
		<truncated>0</truncated>
		<difficult>0</difficult>
		<occluded>0</occluded>
		<bndbox>
			<xmin>410</xmin>
			<xmax>468</xmax>
			<ymin>88</ymin>
			<ymax>145</ymax>
		</bndbox>
	</object>
	<object>
		<name>helmet</name>
		<pose>Unspecified</pose>
		<truncated>0</truncated>
		<difficult>0</difficult>
		<occluded>0</occluded>
		<bndbox>
			<xmin>429</xmin>
			<xmax>497</xmax>
			<ymin>113</ymin>
			<ymax>179</ymax>
		</bndbox>
	</object>
	<object>
		<name>helmet</name>
		<pose>Unspecified</pose>
		<truncated>0</truncated>
		<difficult>0</difficult>
		<occluded>0</occluded>
		<bndbox>
			<xmin>133</xmin>
			<xmax>155</xmax>
			<ymin>103</ymin>
			<ymax>124</ymax>
		</bndbox>
	</object>
</annotation>
