<annotation>
	<folder></folder>
	<filename>002624_jpg.rf.a393cb8276ed338b8c508e830251c93c.jpg</filename>
	<path>002624_jpg.rf.a393cb8276ed338b8c508e830251c93c.jpg</path>
	<source>
		<database>roboflow.ai</database>
	</source>
	<size>
		<width>500</width>
		<height>334</height>
		<depth>3</depth>
	</size>
	<segmented>0</segmented>
	<object>
		<name>helmet</name>
		<pose>Unspecified</pose>
		<truncated>0</truncated>
		<difficult>0</difficult>
		<occluded>0</occluded>
		<bndbox>
			<xmin>389</xmin>
			<xmax>423</xmax>
			<ymin>85</ymin>
			<ymax>126</ymax>
		</bndbox>
	</object>
	<object>
		<name>helmet</name>
		<pose>Unspecified</pose>
		<truncated>0</truncated>
		<difficult>0</difficult>
		<occluded>0</occluded>
		<bndbox>
			<xmin>304</xmin>
			<xmax>331</xmax>
			<ymin>105</ymin>
			<ymax>141</ymax>
		</bndbox>
	</object>
	<object>
		<name>helmet</name>
		<pose>Unspecified</pose>
		<truncated>0</truncated>
		<difficult>0</difficult>
		<occluded>0</occluded>
		<bndbox>
			<xmin>210</xmin>
			<xmax>237</xmax>
			<ymin>119</ymin>
			<ymax>153</ymax>
		</bndbox>
	</object>
	<object>
		<name>helmet</name>
		<pose>Unspecified</pose>
		<truncated>0</truncated>
		<difficult>0</difficult>
		<occluded>0</occluded>
		<bndbox>
			<xmin>126</xmin>
			<xmax>154</xmax>
			<ymin>138</ymin>
			<ymax>172</ymax>
		</bndbox>
	</object>
	<object>
		<name>helmet</name>
		<pose>Unspecified</pose>
		<truncated>0</truncated>
		<difficult>0</difficult>
		<occluded>0</occluded>
		<bndbox>
			<xmin>258</xmin>
			<xmax>285</xmax>
			<ymin>119</ymin>
			<ymax>152</ymax>
		</bndbox>
	</object>
</annotation>
