<annotation>
	<folder></folder>
	<filename>002762_jpg.rf.d96b82e38643c9d534c4c6f7b8d191e2.jpg</filename>
	<path>002762_jpg.rf.d96b82e38643c9d534c4c6f7b8d191e2.jpg</path>
	<source>
		<database>roboflow.ai</database>
	</source>
	<size>
		<width>500</width>
		<height>375</height>
		<depth>3</depth>
	</size>
	<segmented>0</segmented>
	<object>
		<name>helmet</name>
		<pose>Unspecified</pose>
		<truncated>0</truncated>
		<difficult>0</difficult>
		<occluded>0</occluded>
		<bndbox>
			<xmin>259</xmin>
			<xmax>295</xmax>
			<ymin>27</ymin>
			<ymax>77</ymax>
		</bndbox>
	</object>
	<object>
		<name>helmet</name>
		<pose>Unspecified</pose>
		<truncated>0</truncated>
		<difficult>0</difficult>
		<occluded>0</occluded>
		<bndbox>
			<xmin>159</xmin>
			<xmax>195</xmax>
			<ymin>189</ymin>
			<ymax>230</ymax>
		</bndbox>
	</object>
	<object>
		<name>helmet</name>
		<pose>Unspecified</pose>
		<truncated>0</truncated>
		<difficult>0</difficult>
		<occluded>0</occluded>
		<bndbox>
			<xmin>356</xmin>
			<xmax>408</xmax>
			<ymin>76</ymin>
			<ymax>121</ymax>
		</bndbox>
	</object>
	<object>
		<name>helmet</name>
		<pose>Unspecified</pose>
		<truncated>0</truncated>
		<difficult>0</difficult>
		<occluded>0</occluded>
		<bndbox>
			<xmin>119</xmin>
			<xmax>163</xmax>
			<ymin>161</ymin>
			<ymax>218</ymax>
		</bndbox>
	</object>
	<object>
		<name>helmet</name>
		<pose>Unspecified</pose>
		<truncated>0</truncated>
		<difficult>0</difficult>
		<occluded>0</occluded>
		<bndbox>
			<xmin>220</xmin>
			<xmax>250</xmax>
			<ymin>50</ymin>
			<ymax>91</ymax>
		</bndbox>
	</object>
</annotation>
