<annotation>
	<folder></folder>
	<filename>002995_jpg.rf.cee4a79a0be3643ef2e458fbf5ab2980.jpg</filename>
	<path>002995_jpg.rf.cee4a79a0be3643ef2e458fbf5ab2980.jpg</path>
	<source>
		<database>roboflow.ai</database>
	</source>
	<size>
		<width>400</width>
		<height>300</height>
		<depth>3</depth>
	</size>
	<segmented>0</segmented>
	<object>
		<name>helmet</name>
		<pose>Unspecified</pose>
		<truncated>0</truncated>
		<difficult>0</difficult>
		<occluded>0</occluded>
		<bndbox>
			<xmin>217</xmin>
			<xmax>282</xmax>
			<ymin>128</ymin>
			<ymax>196</ymax>
		</bndbox>
	</object>
	<object>
		<name>helmet</name>
		<pose>Unspecified</pose>
		<truncated>0</truncated>
		<difficult>0</difficult>
		<occluded>0</occluded>
		<bndbox>
			<xmin>171</xmin>
			<xmax>227</xmax>
			<ymin>237</ymin>
			<ymax>285</ymax>
		</bndbox>
	</object>
</annotation>
