<annotation>
	<folder></folder>
	<filename>003058_jpg.rf.630b00062f0c9a4bb5c2687c32ea7024.jpg</filename>
	<path>003058_jpg.rf.630b00062f0c9a4bb5c2687c32ea7024.jpg</path>
	<source>
		<database>roboflow.ai</database>
	</source>
	<size>
		<width>500</width>
		<height>750</height>
		<depth>3</depth>
	</size>
	<segmented>0</segmented>
	<object>
		<name>helmet</name>
		<pose>Unspecified</pose>
		<truncated>0</truncated>
		<difficult>0</difficult>
		<occluded>0</occluded>
		<bndbox>
			<xmin>158</xmin>
			<xmax>220</xmax>
			<ymin>382</ymin>
			<ymax>449</ymax>
		</bndbox>
	</object>
	<object>
		<name>helmet</name>
		<pose>Unspecified</pose>
		<truncated>0</truncated>
		<difficult>0</difficult>
		<occluded>0</occluded>
		<bndbox>
			<xmin>248</xmin>
			<xmax>304</xmax>
			<ymin>47</ymin>
			<ymax>112</ymax>
		</bndbox>
	</object>
	<object>
		<name>helmet</name>
		<pose>Unspecified</pose>
		<truncated>0</truncated>
		<difficult>0</difficult>
		<occluded>0</occluded>
		<bndbox>
			<xmin>223</xmin>
			<xmax>275</xmax>
			<ymin>240</ymin>
			<ymax>302</ymax>
		</bndbox>
	</object>
</annotation>
