<annotation>
	<folder></folder>
	<filename>003968_jpg.rf.f0819825074bcfabac5442943f30b450.jpg</filename>
	<path>003968_jpg.rf.f0819825074bcfabac5442943f30b450.jpg</path>
	<source>
		<database>roboflow.ai</database>
	</source>
	<size>
		<width>500</width>
		<height>332</height>
		<depth>3</depth>
	</size>
	<segmented>0</segmented>
	<object>
		<name>helmet</name>
		<pose>Unspecified</pose>
		<truncated>0</truncated>
		<difficult>0</difficult>
		<occluded>0</occluded>
		<bndbox>
			<xmin>260</xmin>
			<xmax>287</xmax>
			<ymin>112</ymin>
			<ymax>145</ymax>
		</bndbox>
	</object>
	<object>
		<name>helmet</name>
		<pose>Unspecified</pose>
		<truncated>0</truncated>
		<difficult>0</difficult>
		<occluded>0</occluded>
		<bndbox>
			<xmin>233</xmin>
			<xmax>258</xmax>
			<ymin>107</ymin>
			<ymax>138</ymax>
		</bndbox>
	</object>
</annotation>
