<annotation>
	<folder></folder>
	<filename>004138_jpg.rf.7c24ed95bee49dde14aba70482b4571a.jpg</filename>
	<path>004138_jpg.rf.7c24ed95bee49dde14aba70482b4571a.jpg</path>
	<source>
		<database>roboflow.ai</database>
	</source>
	<size>
		<width>500</width>
		<height>375</height>
		<depth>3</depth>
	</size>
	<segmented>0</segmented>
	<object>
		<name>head</name>
		<pose>Unspecified</pose>
		<truncated>0</truncated>
		<difficult>0</difficult>
		<occluded>0</occluded>
		<bndbox>
			<xmin>261</xmin>
			<xmax>307</xmax>
			<ymin>111</ymin>
			<ymax>163</ymax>
		</bndbox>
	</object>
	<object>
		<name>head</name>
		<pose>Unspecified</pose>
		<truncated>0</truncated>
		<difficult>0</difficult>
		<occluded>0</occluded>
		<bndbox>
			<xmin>357</xmin>
			<xmax>393</xmax>
			<ymin>119</ymin>
			<ymax>170</ymax>
		</bndbox>
	</object>
	<object>
		<name>head</name>
		<pose>Unspecified</pose>
		<truncated>0</truncated>
		<difficult>0</difficult>
		<occluded>0</occluded>
		<bndbox>
			<xmin>177</xmin>
			<xmax>210</xmax>
			<ymin>133</ymin>
			<ymax>172</ymax>
		</bndbox>
	</object>
	<object>
		<name>head</name>
		<pose>Unspecified</pose>
		<truncated>0</truncated>
		<difficult>0</difficult>
		<occluded>0</occluded>
		<bndbox>
			<xmin>86</xmin>
			<xmax>125</xmax>
			<ymin>118</ymin>
			<ymax>164</ymax>
		</bndbox>
	</object>
	<object>
		<name>head</name>
		<pose>Unspecified</pose>
		<truncated>0</truncated>
		<difficult>0</difficult>
		<occluded>0</occluded>
		<bndbox>
			<xmin>387</xmin>
			<xmax>434</xmax>
			<ymin>126</ymin>
			<ymax>181</ymax>
		</bndbox>
	</object>
	<object>
		<name>head</name>
		<pose>Unspecified</pose>
		<truncated>0</truncated>
		<difficult>0</difficult>
		<occluded>0</occluded>
		<bndbox>
			<xmin>1</xmin>
			<xmax>26</xmax>
			<ymin>123</ymin>
			<ymax>176</ymax>
		</bndbox>
	</object>
</annotation>
