<annotation>
	<folder></folder>
	<filename>004670_jpg.rf.7a94e72cfd00e08607c9b451ee3516f4.jpg</filename>
	<path>004670_jpg.rf.7a94e72cfd00e08607c9b451ee3516f4.jpg</path>
	<source>
		<database>roboflow.ai</database>
	</source>
	<size>
		<width>497</width>
		<height>345</height>
		<depth>3</depth>
	</size>
	<segmented>0</segmented>
	<object>
		<name>helmet</name>
		<pose>Unspecified</pose>
		<truncated>0</truncated>
		<difficult>0</difficult>
		<occluded>0</occluded>
		<bndbox>
			<xmin>153</xmin>
			<xmax>284</xmax>
			<ymin>2</ymin>
			<ymax>135</ymax>
		</bndbox>
	</object>
	<object>
		<name>helmet</name>
		<pose>Unspecified</pose>
		<truncated>0</truncated>
		<difficult>0</difficult>
		<occluded>0</occluded>
		<bndbox>
			<xmin>457</xmin>
			<xmax>497</xmax>
			<ymin>19</ymin>
			<ymax>138</ymax>
		</bndbox>
	</object>
</annotation>
