<annotation>
	<folder></folder>
	<filename>004865_jpg.rf.c450b6680b18a65072a4d532b4dc73ad.jpg</filename>
	<path>004865_jpg.rf.c450b6680b18a65072a4d532b4dc73ad.jpg</path>
	<source>
		<database>roboflow.ai</database>
	</source>
	<size>
		<width>500</width>
		<height>333</height>
		<depth>3</depth>
	</size>
	<segmented>0</segmented>
	<object>
		<name>helmet</name>
		<pose>Unspecified</pose>
		<truncated>0</truncated>
		<difficult>0</difficult>
		<occluded>0</occluded>
		<bndbox>
			<xmin>338</xmin>
			<xmax>405</xmax>
			<ymin>118</ymin>
			<ymax>185</ymax>
		</bndbox>
	</object>
</annotation>
